streamfuels/__init__.py
streamfuels/datasets/__init__.py
streamfuels/datasets/auxiliary_functions.py
streamfuels/datasets/dataset_loader.py
streamfuels/datasets/extract.py
streamfuels/datasets/transform.py
streamfuels-0.1.3.dist-info/METADATA
streamfuels-0.1.3.dist-info/WHEEL
streamfuels-0.1.3.dist-info/top_level.txt
streamfuels-0.1.3.dist-info/RECORD
