Metadata-Version: 2.4
Name: streamfuels
Version: 0.1.3
Summary: Data processing and analysis tools for fuel market research
Home-page: https://github.com/streamfuels/streamfuels
Author: StreamFuels
Author-email: lucascstxv@gmail.com
License: MIT
Classifier: Programming Language :: Python :: 3
Classifier: License :: OSI Approved :: MIT License
Classifier: Operating System :: OS Independent
Requires-Python: >=3.9
Requires-Dist: pandas>=1.2.0
Requires-Dist: requests>=2.25.0
Requires-Dist: beautifulsoup4>=4.9.0
Requires-Dist: unidecode>=1.1.1
Requires-Dist: numpy>=1.19.0
Requires-Dist: editdistance>=0.5.3
Requires-Dist: setuptools
Requires-Dist: tqdm==4.65.0
Dynamic: author
Dynamic: author-email
Dynamic: classifier
Dynamic: description
Dynamic: description-content-type
Dynamic: home-page
Dynamic: license
Dynamic: requires-dist
Dynamic: requires-python
Dynamic: summary
